qrm_client/__init__.py
qrm_client/qrm_http_client.py
qrm_client/ver.yaml
qrm_defs/__init__.py
qrm_defs/qrm_urls.py
qrm_defs/resource_definition.py
qrm_client-0.2.5.dist-info/LICENSE
qrm_client-0.2.5.dist-info/METADATA
qrm_client-0.2.5.dist-info/WHEEL
qrm_client-0.2.5.dist-info/top_level.txt
qrm_client-0.2.5.dist-info/RECORD
