Metadata-Version: 2.1
Name: qrm-client
Version: 0.2.5
Summary: qrm_client
Home-page: https://github.com/final-israel/qrm
Author: iPerf
Author-email: pavelr@final.israel
License: UNKNOWN
Platform: UNKNOWN
Classifier: Programming Language :: Python :: 3.6
Classifier: Programming Language :: Python :: 3.7
Classifier: Programming Language :: Python :: 3.8
Classifier: Programming Language :: Python :: 3.9
Classifier: Programming Language :: Python :: 3.10
Requires-Python: >=3.6.9
Requires-Dist: dataclass-type-validator
Requires-Dist: dataclasses
Requires-Dist: requests
Requires-Dist: pyyaml
Requires-Dist: dataclasses-json
